{
  "1INCH": [
    {
      "price": 0.0885,
      "volume": 413575.16006
    },
    {
      "price": 0.0885,
      "volume": 413575.16006
    }
  ],
  "AAVE": [
    {
      "price": 101.42,
      "volume": 10017409.69872
    },
    {
      "price": 101.42,
      "volume": 10017409.69872
    }
  ],
  "ACH": [
    {
      "price": 0.00636,
      "volume": 432945.60404
    },
    {
      "price": 0.00636,
      "volume": 432945.60404
    }
  ],
  "ADA": [
    {
      "price": 0.2463,
      "volume": 42192954.49085
    },
    {
      "price": 0.2463,
      "volume": 42192954.49085
    }
  ],
  "AEVO": [
    {
      "price": 0.0245,
      "volume": 481900.768871
    },
    {
      "price": 0.0245,
      "volume": 481900.768871
    }
  ],
  "AI": [
    {
      "price": 0.0187,
      "volume": 299990.20751
    },
    {
      "price": 0.0187,
      "volume": 299990.20751
    }
  ],
  "AIXBT": [
    {
      "price": 0.0245,
      "volume": 1529997.1876
    },
    {
      "price": 0.0245,
      "volume": 1529997.1876
    }
  ],
  "ALGO": [
    {
      "price": 0.0814,
      "volume": 1487900.8106
    },
    {
      "price": 0.0814,
      "volume": 1487900.8106
    }
  ],
  "ALT": [
    {
      "price": 0.00643,
      "volume": 470233.67132
    },
    {
      "price": 0.00643,
      "volume": 470233.67132
    }
  ],
  "AMP": [
    {
      "price": 0.001104,
      "volume": 650159.208425
    },
    {
      "price": 0.001104,
      "volume": 650159.208425
    }
  ],
  "ANIME": [
    {
      "price": 0.00464,
      "volume": 470453.621306
    },
    {
      "price": 0.00464,
      "volume": 470453.621306
    }
  ],
  "ANKR": [
    {
      "price": 0.00496,
      "volume": 5902123.154878
    },
    {
      "price": 0.00496,
      "volume": 5902123.154878
    }
  ],
  "API3": [
    {
      "price": 0.27,
      "volume": 401688.109984
    },
    {
      "price": 0.27,
      "volume": 401688.109984
    }
  ],
  "ARKM": [
    {
      "price": 0.098,
      "volume": 1290091.0594
    },
    {
      "price": 0.098,
      "volume": 1290091.0594
    }
  ],
  "ASTER": [
    {
      "price": 0.655,
      "volume": 7655542.24664
    },
    {
      "price": 0.655,
      "volume": 7655542.24664
    }
  ],
  "ATOM": [
    {
      "price": 1.663,
      "volume": 2728403.09623
    },
    {
      "price": 1.663,
      "volume": 2728403.09623
    }
  ],
  "AUCTION": [
    {
      "price": 4.43,
      "volume": 301143.5638
    },
    {
      "price": 4.43,
      "volume": 301143.5638
    }
  ],
  "AVAX": [
    {
      "price": 8.7,
      "volume": 20893969.0096
    },
    {
      "price": 8.7,
      "volume": 20893969.0096
    }
  ],
  "AVNT": [
    {
      "price": 0.1371,
      "volume": 1721140.78704
    },
    {
      "price": 0.1371,
      "volume": 1721140.78704
    }
  ],
  "AXL": [
    {
      "price": 0.0472,
      "volume": 707394.766356
    },
    {
      "price": 0.0472,
      "volume": 707394.766356
    }
  ],
  "BADGER": [
    {
      "price": 0.762,
      "volume": 183491.40946
    },
    {
      "price": 0.762,
      "volume": 183491.40946
    }
  ],
  "BAKE": [
    {
      "price": 0.0519,
      "volume": 711688.37986
    },
    {
      "price": 0.0519,
      "volume": 711688.37986
    }
  ],
  "BAND": [
    {
      "price": 0.207,
      "volume": 150563.3786
    },
    {
      "price": 0.207,
      "volume": 150563.3786
    }
  ],
  "BAT": [
    {
      "price": 0.0968,
      "volume": 798966.4115
    },
    {
      "price": 0.0968,
      "volume": 798966.4115
    }
  ],
  "BEAM": [
    {
      "price": 0.0652,
      "volume": 739250.4197
    },
    {
      "price": 0.0652,
      "volume": 739250.4197
    }
  ],
  "BETA": [
    {
      "price": 0.00036,
      "volume": 296136.47499
    },
    {
      "price": 0.00036,
      "volume": 296136.47499
    }
  ],
  "BLUR": [
    {
      "price": 0.01769,
      "volume": 168274.532291
    },
    {
      "price": 0.01769,
      "volume": 168274.532291
    }
  ],
  "BMT": [
    {
      "price": 0.01448,
      "volume": 106792.741034
    },
    {
      "price": 0.01448,
      "volume": 106792.741034
    }
  ],
  "BNB": [
    {
      "price": 609.93,
      "volume": 74130034.06627
    },
    {
      "price": 609.93,
      "volume": 74130034.06627
    }
  ],
  "BONK": [
    {
      "price": 0.00000573,
      "volume": 5204995.46168187
    },
    {
      "price": 0.00000573,
      "volume": 5204995.46168187
    }
  ],
  "BTT": [
    {
      "price": 0,
      "volume": 0
    },
    {
      "price": 0,
      "volume": 0
    }
  ],
  "C98": [
    {
      "price": 0.0258,
      "volume": 256359.31977
    },
    {
      "price": 0.0258,
      "volume": 256359.31977
    }
  ],
  "CELO": [
    {
      "price": 0.0797,
      "volume": 650475.99357
    },
    {
      "price": 0.0797,
      "volume": 650475.99357
    }
  ],
  "CELR": [
    {
      "price": 0.002494,
      "volume": 632623.3243383
    },
    {
      "price": 0.002494,
      "volume": 632623.3243383
    }
  ],
  "CFX": [
    {
      "price": 0.05792,
      "volume": 1877978.7897
    },
    {
      "price": 0.05792,
      "volume": 1877978.7897
    }
  ],
  "CGPT": [
    {
      "price": 0.01955,
      "volume": 353725.046681
    },
    {
      "price": 0.01955,
      "volume": 353725.046681
    }
  ],
  "COMP": [
    {
      "price": 18.31,
      "volume": 425324.69566
    },
    {
      "price": 18.31,
      "volume": 425324.69566
    }
  ],
  "COTI": [
    {
      "price": 0.01242,
      "volume": 586088.77928
    },
    {
      "price": 0.01242,
      "volume": 586088.77928
    }
  ],
  "COW": [
    {
      "price": 0.1961,
      "volume": 1139205.9303
    },
    {
      "price": 0.1961,
      "volume": 1139205.9303
    }
  ],
  "CRV": [
    {
      "price": 0.2163,
      "volume": 4439690.15871
    },
    {
      "price": 0.2163,
      "volume": 4439690.15871
    }
  ],
  "CVX": [
    {
      "price": 1.66,
      "volume": 818261.522727
    },
    {
      "price": 1.66,
      "volume": 818261.522727
    }
  ],
  "CYBER": [
    {
      "price": 0.495,
      "volume": 392168.32352
    },
    {
      "price": 0.495,
      "volume": 392168.32352
    }
  ],
  "DNT": [
    {
      "price": 0.036,
      "volume": 775093.2743
    },
    {
      "price": 0.036,
      "volume": 775093.2743
    }
  ],
  "DOGS": [
    {
      "price": 0.0000264,
      "volume": 234954.028959
    },
    {
      "price": 0.0000264,
      "volume": 234954.028959
    }
  ],
  "DUSK": [
    {
      "price": 0.1075,
      "volume": 1906620.1267
    },
    {
      "price": 0.1075,
      "volume": 1906620.1267
    }
  ],
  "EGLD": [
    {
      "price": 3.83,
      "volume": 939098.0895
    },
    {
      "price": 3.83,
      "volume": 939098.0895
    }
  ],
  "ENJ": [
    {
      "price": 0.0209,
      "volume": 4566659.068068
    },
    {
      "price": 0.0209,
      "volume": 4566659.068068
    }
  ],
  "ENS": [
    {
      "price": 5.64,
      "volume": 789795.3524
    },
    {
      "price": 5.64,
      "volume": 789795.3524
    }
  ],
  "ETHFI": [
    {
      "price": 0.473,
      "volume": 4337532.4294
    },
    {
      "price": 0.473,
      "volume": 4337532.4294
    }
  ],
  "FET": [
    {
      "price": 0.2311,
      "volume": 17614374.38823
    },
    {
      "price": 0.2311,
      "volume": 17614374.38823
    }
  ],
  "FF": [
    {
      "price": 0.07025,
      "volume": 760544.351177
    },
    {
      "price": 0.07025,
      "volume": 760544.351177
    }
  ],
  "FIL": [
    {
      "price": 0.838,
      "volume": 10538431.40771
    },
    {
      "price": 0.838,
      "volume": 10538431.40771
    }
  ],
  "FLOKI": [
    {
      "price": 0.00002797,
      "volume": 2221385.11335614
    },
    {
      "price": 0.00002797,
      "volume": 2221385.11335614
    }
  ],
  "FUN": [
    {
      "price": 0.001344,
      "volume": 642189.73304
    },
    {
      "price": 0.001344,
      "volume": 642189.73304
    }
  ],
  "G": [
    {
      "price": 0.00349,
      "volume": 495645.64427
    },
    {
      "price": 0.00349,
      "volume": 495645.64427
    }
  ],
  "GMT": [
    {
      "price": 0.00983,
      "volume": 441256.305879
    },
    {
      "price": 0.00983,
      "volume": 441256.305879
    }
  ],
  "GMX": [
    {
      "price": 6.17,
      "volume": 259410.54356
    },
    {
      "price": 6.17,
      "volume": 259410.54356
    }
  ],
  "GNS": [
    {
      "price": 0.732,
      "volume": 121181.48806
    },
    {
      "price": 0.732,
      "volume": 121181.48806
    }
  ],
  "GTC": [
    {
      "price": 0.082,
      "volume": 439697.148
    },
    {
      "price": 0.082,
      "volume": 439697.148
    }
  ],
  "HAEDAL": [
    {
      "price": 0.029,
      "volume": 345093.25646
    },
    {
      "price": 0.029,
      "volume": 345093.25646
    }
  ],
  "HIFI": [
    {
      "price": 0.127,
      "volume": 879729.93804
    },
    {
      "price": 0.127,
      "volume": 879729.93804
    }
  ],
  "HIGH": [
    {
      "price": 0.123,
      "volume": 240468.867351
    },
    {
      "price": 0.123,
      "volume": 240468.867351
    }
  ],
  "HIVE": [
    {
      "price": 0.0578,
      "volume": 342212.5556
    },
    {
      "price": 0.0578,
      "volume": 342212.5556
    }
  ],
  "HOME": [
    {
      "price": 0.01917,
      "volume": 432131.85288
    },
    {
      "price": 0.01917,
      "volume": 432131.85288
    }
  ],
  "HUMA": [
    {
      "price": 0.01642,
      "volume": 3917777.84549
    },
    {
      "price": 0.01642,
      "volume": 3917777.84549
    }
  ],
  "HYPER": [
    {
      "price": 0.0849,
      "volume": 395646.62014
    },
    {
      "price": 0.0849,
      "volume": 395646.62014
    }
  ],
  "ICP": [
    {
      "price": 2.228,
      "volume": 4929693.39584
    },
    {
      "price": 2.228,
      "volume": 4929693.39584
    }
  ],
  "IMX": [
    {
      "price": 0.1464,
      "volume": 1444835.849656
    },
    {
      "price": 0.1464,
      "volume": 1444835.849656
    }
  ],
  "INJ": [
    {
      "price": 2.881,
      "volume": 1831607.37101
    },
    {
      "price": 2.881,
      "volume": 1831607.37101
    }
  ],
  "IO": [
    {
      "price": 0.112,
      "volume": 1202723.87391
    },
    {
      "price": 0.112,
      "volume": 1202723.87391
    }
  ],
  "IOST": [
    {
      "price": 0.001051,
      "volume": 117938.367591
    },
    {
      "price": 0.001051,
      "volume": 117938.367591
    }
  ],
  "IOTX": [
    {
      "price": 0.00484,
      "volume": 421421.01411
    },
    {
      "price": 0.00484,
      "volume": 421421.01411
    }
  ],
  "IQ": [
    {
      "price": 0.001053,
      "volume": 243578.920306
    },
    {
      "price": 0.001053,
      "volume": 243578.920306
    }
  ],
  "JASMY": [
    {
      "price": 0.00544,
      "volume": 1187902.077694
    },
    {
      "price": 0.00544,
      "volume": 1187902.077694
    }
  ],
  "JUP": [
    {
      "price": 0.1431,
      "volume": 3175635.04464
    },
    {
      "price": 0.1431,
      "volume": 3175635.04464
    }
  ],
  "KAIA": [
    {
      "price": 0.0469,
      "volume": 927425.93998
    },
    {
      "price": 0.0469,
      "volume": 927425.93998
    }
  ],
  "KERNEL": [
    {
      "price": 0.0874,
      "volume": 629880.05652
    },
    {
      "price": 0.0874,
      "volume": 629880.05652
    }
  ],
  "KITE": [
    {
      "price": 0.2042,
      "volume": 16179590.4953
    },
    {
      "price": 0.2042,
      "volume": 16179590.4953
    }
  ],
  "KMNO": [
    {
      "price": 0.01826,
      "volume": 283592.61615
    },
    {
      "price": 0.01826,
      "volume": 283592.61615
    }
  ],
  "KNC": [
    {
      "price": 0.169,
      "volume": 5245146.7862
    },
    {
      "price": 0.169,
      "volume": 5245146.7862
    }
  ],
  "LDO": [
    {
      "price": 0.2755,
      "volume": 1632209.514148
    },
    {
      "price": 0.2755,
      "volume": 1632209.514148
    }
  ],
  "LISTA": [
    {
      "price": 0.08,
      "volume": 166880.17898
    },
    {
      "price": 0.08,
      "volume": 166880.17898
    }
  ],
  "LIT": [
    {
      "price": 0.743,
      "volume": 799655.0663
    },
    {
      "price": 0.743,
      "volume": 799655.0663
    }
  ],
  "LPT": [
    {
      "price": 2.09,
      "volume": 638702.78771
    },
    {
      "price": 2.09,
      "volume": 638702.78771
    }
  ],
  "LQTY": [
    {
      "price": 0.267,
      "volume": 160609.4188
    },
    {
      "price": 0.267,
      "volume": 160609.4188
    }
  ],
  "LRC": [
    {
      "price": 0.02299,
      "volume": 567042.222
    },
    {
      "price": 0.02299,
      "volume": 567042.222
    }
  ],
  "LUNC": [
    {
      "price": 0.00003693,
      "volume": 1476075.26870079
    },
    {
      "price": 0.00003693,
      "volume": 1476075.26870079
    }
  ],
  "MANA": [
    {
      "price": 0.0813,
      "volume": 498655.5147
    },
    {
      "price": 0.0813,
      "volume": 498655.5147
    }
  ],
  "MASK": [
    {
      "price": 0.414,
      "volume": 277026.5953
    },
    {
      "price": 0.414,
      "volume": 277026.5953
    }
  ],
  "MBOX": [
    {
      "price": 0.0154,
      "volume": 519523.43725
    },
    {
      "price": 0.0154,
      "volume": 519523.43725
    }
  ],
  "ME": [
    {
      "price": 0.0992,
      "volume": 378463.01392
    },
    {
      "price": 0.0992,
      "volume": 378463.01392
    }
  ]
}