{
  "1INCH": [
    {
      "price": 0.0871,
      "volume": 385850.00678
    },
    {
      "price": 0.0871,
      "volume": 385850.00678
    }
  ],
  "AAVE": [
    {
      "price": 94.89,
      "volume": 2668477.21282
    },
    {
      "price": 94.89,
      "volume": 2668477.21282
    }
  ],
  "ACH": [
    {
      "price": 0.00627,
      "volume": 3098040.25251
    },
    {
      "price": 0.00627,
      "volume": 3098040.25251
    }
  ],
  "ADA": [
    {
      "price": 0.2483,
      "volume": 26076281.17022
    },
    {
      "price": 0.2483,
      "volume": 26076281.17022
    }
  ],
  "AEVO": [
    {
      "price": 0.0227,
      "volume": 4648922.720397
    },
    {
      "price": 0.0227,
      "volume": 4648922.720397
    }
  ],
  "AI": [
    {
      "price": 0.0198,
      "volume": 1128390.28617
    },
    {
      "price": 0.0198,
      "volume": 1128390.28617
    }
  ],
  "AIXBT": [
    {
      "price": 0.0226,
      "volume": 1143617.56863
    },
    {
      "price": 0.0226,
      "volume": 1143617.56863
    }
  ],
  "ALGO": [
    {
      "price": 0.1236,
      "volume": 22033469.6931
    },
    {
      "price": 0.1236,
      "volume": 22033469.6931
    }
  ],
  "ALT": [
    {
      "price": 0.00656,
      "volume": 6605355.69574
    },
    {
      "price": 0.00656,
      "volume": 6605355.69574
    }
  ],
  "AMP": [
    {
      "price": 0.000968,
      "volume": 924607.253584
    },
    {
      "price": 0.000968,
      "volume": 924607.253584
    }
  ],
  "ANIME": [
    {
      "price": 0.00453,
      "volume": 498188.320627
    },
    {
      "price": 0.00453,
      "volume": 498188.320627
    }
  ],
  "ANKR": [
    {
      "price": 0.00504,
      "volume": 1259235.363516
    },
    {
      "price": 0.00504,
      "volume": 1259235.363516
    }
  ],
  "API3": [
    {
      "price": 0.2686,
      "volume": 353968.691316
    },
    {
      "price": 0.2686,
      "volume": 353968.691316
    }
  ],
  "ARKM": [
    {
      "price": 0.097,
      "volume": 926382.9848
    },
    {
      "price": 0.097,
      "volume": 926382.9848
    }
  ],
  "ASTER": [
    {
      "price": 0.654,
      "volume": 7236082.50456
    },
    {
      "price": 0.654,
      "volume": 7236082.50456
    }
  ],
  "ATOM": [
    {
      "price": 1.698,
      "volume": 1428726.41864
    },
    {
      "price": 1.698,
      "volume": 1428726.41864
    }
  ],
  "AUCTION": [
    {
      "price": 4.66,
      "volume": 268901.4264
    },
    {
      "price": 4.66,
      "volume": 268901.4264
    }
  ],
  "AVAX": [
    {
      "price": 8.95,
      "volume": 14031224.6186
    },
    {
      "price": 8.95,
      "volume": 14031224.6186
    }
  ],
  "AVNT": [
    {
      "price": 0.1247,
      "volume": 495044.8308
    },
    {
      "price": 0.1247,
      "volume": 495044.8308
    }
  ],
  "AXL": [
    {
      "price": 0.0438,
      "volume": 716968.739347
    },
    {
      "price": 0.0438,
      "volume": 716968.739347
    }
  ],
  "BADGER": [
    {
      "price": 0.762,
      "volume": 183491.40946
    },
    {
      "price": 0.762,
      "volume": 183491.40946
    }
  ],
  "BAKE": [
    {
      "price": 0.0519,
      "volume": 711688.37986
    },
    {
      "price": 0.0519,
      "volume": 711688.37986
    }
  ],
  "BAND": [
    {
      "price": 0.211,
      "volume": 309666.2936
    },
    {
      "price": 0.211,
      "volume": 309666.2936
    }
  ],
  "BAT": [
    {
      "price": 0.0958,
      "volume": 241026.4648
    },
    {
      "price": 0.0958,
      "volume": 241026.4648
    }
  ],
  "BEAM": [
    {
      "price": 0.0652,
      "volume": 739250.4197
    },
    {
      "price": 0.0652,
      "volume": 739250.4197
    }
  ],
  "BETA": [
    {
      "price": 0.00036,
      "volume": 296136.47499
    },
    {
      "price": 0.00036,
      "volume": 296136.47499
    }
  ],
  "BLUR": [
    {
      "price": 0.01985,
      "volume": 2008442.323846
    },
    {
      "price": 0.01985,
      "volume": 2008442.323846
    }
  ],
  "BMT": [
    {
      "price": 0.01472,
      "volume": 797180.567525
    },
    {
      "price": 0.01472,
      "volume": 797180.567525
    }
  ],
  "BNB": [
    {
      "price": 588.51,
      "volume": 47118938.49047
    },
    {
      "price": 588.51,
      "volume": 47118938.49047
    }
  ],
  "BONK": [
    {
      "price": 0.00000575,
      "volume": 2805109.18185964
    },
    {
      "price": 0.00000575,
      "volume": 2805109.18185964
    }
  ],
  "BTT": [
    {
      "price": 0,
      "volume": 0
    },
    {
      "price": 0,
      "volume": 0
    }
  ],
  "C98": [
    {
      "price": 0.0248,
      "volume": 207509.83916
    },
    {
      "price": 0.0248,
      "volume": 207509.83916
    }
  ],
  "CELO": [
    {
      "price": 0.085,
      "volume": 713287.04054
    },
    {
      "price": 0.085,
      "volume": 713287.04054
    }
  ],
  "CELR": [
    {
      "price": 0.002513,
      "volume": 500016.7766707
    },
    {
      "price": 0.002513,
      "volume": 500016.7766707
    }
  ],
  "CFX": [
    {
      "price": 0.05239,
      "volume": 1164500.47582
    },
    {
      "price": 0.05239,
      "volume": 1164500.47582
    }
  ],
  "CGPT": [
    {
      "price": 0.01851,
      "volume": 219420.234627
    },
    {
      "price": 0.01851,
      "volume": 219420.234627
    }
  ],
  "COMP": [
    {
      "price": 16.95,
      "volume": 704712.03463
    },
    {
      "price": 16.95,
      "volume": 704712.03463
    }
  ],
  "COTI": [
    {
      "price": 0.01382,
      "volume": 772322.85095
    },
    {
      "price": 0.01382,
      "volume": 772322.85095
    }
  ],
  "COW": [
    {
      "price": 0.2016,
      "volume": 322443.98643
    },
    {
      "price": 0.2016,
      "volume": 322443.98643
    }
  ],
  "CRV": [
    {
      "price": 0.2113,
      "volume": 2702305.60243
    },
    {
      "price": 0.2113,
      "volume": 2702305.60243
    }
  ],
  "CVX": [
    {
      "price": 1.712,
      "volume": 361155.744347
    },
    {
      "price": 1.712,
      "volume": 361155.744347
    }
  ],
  "CYBER": [
    {
      "price": 0.488,
      "volume": 400189.93788
    },
    {
      "price": 0.488,
      "volume": 400189.93788
    }
  ],
  "DNT": [
    {
      "price": 0.036,
      "volume": 775093.2743
    },
    {
      "price": 0.036,
      "volume": 775093.2743
    }
  ],
  "DOGS": [
    {
      "price": 0.0000273,
      "volume": 282807.1991987
    },
    {
      "price": 0.0000273,
      "volume": 282807.1991987
    }
  ],
  "DUSK": [
    {
      "price": 0.1125,
      "volume": 1344954.1495
    },
    {
      "price": 0.1125,
      "volume": 1344954.1495
    }
  ],
  "EGLD": [
    {
      "price": 3.77,
      "volume": 477670.795
    },
    {
      "price": 3.77,
      "volume": 477670.795
    }
  ],
  "ENJ": [
    {
      "price": 0.02009,
      "volume": 1004357.257321
    },
    {
      "price": 0.02009,
      "volume": 1004357.257321
    }
  ],
  "ENS": [
    {
      "price": 5.54,
      "volume": 535166.0814
    },
    {
      "price": 5.54,
      "volume": 535166.0814
    }
  ],
  "ETHFI": [
    {
      "price": 0.439,
      "volume": 2046220.8618
    },
    {
      "price": 0.439,
      "volume": 2046220.8618
    }
  ],
  "FET": [
    {
      "price": 0.2335,
      "volume": 14735834.88489
    },
    {
      "price": 0.2335,
      "volume": 14735834.88489
    }
  ],
  "FF": [
    {
      "price": 0.06913,
      "volume": 612376.745992
    },
    {
      "price": 0.06913,
      "volume": 612376.745992
    }
  ],
  "FIL": [
    {
      "price": 0.84,
      "volume": 5279348.46211
    },
    {
      "price": 0.84,
      "volume": 5279348.46211
    }
  ],
  "FLOKI": [
    {
      "price": 0.00002692,
      "volume": 1294032.89208065
    },
    {
      "price": 0.00002692,
      "volume": 1294032.89208065
    }
  ],
  "FUN": [
    {
      "price": 0.001404,
      "volume": 771198.139274
    },
    {
      "price": 0.001404,
      "volume": 771198.139274
    }
  ],
  "G": [
    {
      "price": 0.00349,
      "volume": 620480.18933
    },
    {
      "price": 0.00349,
      "volume": 620480.18933
    }
  ],
  "GMT": [
    {
      "price": 0.01018,
      "volume": 658940.260039
    },
    {
      "price": 0.01018,
      "volume": 658940.260039
    }
  ],
  "GMX": [
    {
      "price": 6.04,
      "volume": 224198.91014
    },
    {
      "price": 6.04,
      "volume": 224198.91014
    }
  ],
  "GNS": [
    {
      "price": 0.722,
      "volume": 62877.07054
    },
    {
      "price": 0.722,
      "volume": 62877.07054
    }
  ],
  "GTC": [
    {
      "price": 0.073,
      "volume": 381223.6426
    },
    {
      "price": 0.073,
      "volume": 381223.6426
    }
  ],
  "HAEDAL": [
    {
      "price": 0.0288,
      "volume": 692816.60565
    },
    {
      "price": 0.0288,
      "volume": 692816.60565
    }
  ],
  "HIFI": [
    {
      "price": 0.127,
      "volume": 879729.93804
    },
    {
      "price": 0.127,
      "volume": 879729.93804
    }
  ],
  "HIGH": [
    {
      "price": 0.136,
      "volume": 427832.742202
    },
    {
      "price": 0.136,
      "volume": 427832.742202
    }
  ],
  "HIVE": [
    {
      "price": 0.0598,
      "volume": 473467.8391
    },
    {
      "price": 0.0598,
      "volume": 473467.8391
    }
  ],
  "HOME": [
    {
      "price": 0.02007,
      "volume": 756933.02868
    },
    {
      "price": 0.02007,
      "volume": 756933.02868
    }
  ],
  "HUMA": [
    {
      "price": 0.01452,
      "volume": 3995681.52058
    },
    {
      "price": 0.01452,
      "volume": 3995681.52058
    }
  ],
  "HYPER": [
    {
      "price": 0.0855,
      "volume": 380992.87825
    },
    {
      "price": 0.0855,
      "volume": 380992.87825
    }
  ],
  "ICP": [
    {
      "price": 2.286,
      "volume": 4152302.09208
    },
    {
      "price": 2.286,
      "volume": 4152302.09208
    }
  ],
  "IMX": [
    {
      "price": 0.1338,
      "volume": 874306.352745
    },
    {
      "price": 0.1338,
      "volume": 874306.352745
    }
  ],
  "INJ": [
    {
      "price": 2.814,
      "volume": 1772736.08005
    },
    {
      "price": 2.814,
      "volume": 1772736.08005
    }
  ],
  "IO": [
    {
      "price": 0.1,
      "volume": 736040.27304
    },
    {
      "price": 0.1,
      "volume": 736040.27304
    }
  ],
  "IOST": [
    {
      "price": 0.001088,
      "volume": 135184.982693
    },
    {
      "price": 0.001088,
      "volume": 135184.982693
    }
  ],
  "IOTX": [
    {
      "price": 0.00455,
      "volume": 187723.28038
    },
    {
      "price": 0.00455,
      "volume": 187723.28038
    }
  ],
  "IQ": [
    {
      "price": 0.001042,
      "volume": 154780.489177
    },
    {
      "price": 0.001042,
      "volume": 154780.489177
    }
  ],
  "JASMY": [
    {
      "price": 0.00532,
      "volume": 453492.721825
    },
    {
      "price": 0.00532,
      "volume": 453492.721825
    }
  ],
  "JUP": [
    {
      "price": 0.1632,
      "volume": 2686886.99312
    },
    {
      "price": 0.1632,
      "volume": 2686886.99312
    }
  ],
  "KAIA": [
    {
      "price": 0.0488,
      "volume": 602191.0016
    },
    {
      "price": 0.0488,
      "volume": 602191.0016
    }
  ],
  "KERNEL": [
    {
      "price": 0.1135,
      "volume": 2645611.93647
    },
    {
      "price": 0.1135,
      "volume": 2645611.93647
    }
  ],
  "KITE": [
    {
      "price": 0.1394,
      "volume": 12073285.44505
    },
    {
      "price": 0.1394,
      "volume": 12073285.44505
    }
  ],
  "KMNO": [
    {
      "price": 0.01759,
      "volume": 324801.4633
    },
    {
      "price": 0.01759,
      "volume": 324801.4633
    }
  ],
  "KNC": [
    {
      "price": 0.1288,
      "volume": 294937.64606
    },
    {
      "price": 0.1288,
      "volume": 294937.64606
    }
  ],
  "LDO": [
    {
      "price": 0.3151,
      "volume": 1822387.340983
    },
    {
      "price": 0.3151,
      "volume": 1822387.340983
    }
  ],
  "LISTA": [
    {
      "price": 0.0916,
      "volume": 534936.54255
    },
    {
      "price": 0.0916,
      "volume": 534936.54255
    }
  ],
  "LIT": [
    {
      "price": 0.743,
      "volume": 799655.0663
    },
    {
      "price": 0.743,
      "volume": 799655.0663
    }
  ],
  "LPT": [
    {
      "price": 2.026,
      "volume": 289248.294
    },
    {
      "price": 2.026,
      "volume": 289248.294
    }
  ],
  "LQTY": [
    {
      "price": 0.27,
      "volume": 213271.4616
    },
    {
      "price": 0.27,
      "volume": 213271.4616
    }
  ],
  "LRC": [
    {
      "price": 0.01879,
      "volume": 2891178.19849
    },
    {
      "price": 0.01879,
      "volume": 2891178.19849
    }
  ],
  "LUNC": [
    {
      "price": 0.00003675,
      "volume": 2348634.34495976
    },
    {
      "price": 0.00003675,
      "volume": 2348634.34495976
    }
  ],
  "MANA": [
    {
      "price": 0.0871,
      "volume": 391724.5171
    },
    {
      "price": 0.0871,
      "volume": 391724.5171
    }
  ],
  "MASK": [
    {
      "price": 0.446,
      "volume": 2671288.915
    },
    {
      "price": 0.446,
      "volume": 2671288.915
    }
  ],
  "MBOX": [
    {
      "price": 0.0128,
      "volume": 499673.1542
    },
    {
      "price": 0.0128,
      "volume": 499673.1542
    }
  ],
  "ME": [
    {
      "price": 0.1008,
      "volume": 718492.247014
    },
    {
      "price": 0.1008,
      "volume": 718492.247014
    }
  ]
}