{
  "DENT": [
    {
      "price": 1,
      "volume": 7302922
    },
    {
      "price": 1,
      "volume": 7302922
    }
  ],
  "SPELL": [
    {
      "price": 2.9,
      "volume": 2563366
    },
    {
      "price": 2.9,
      "volume": 2563366
    }
  ],
  "LUNC": [
    {
      "price": 1.22191,
      "volume": 503593446
    },
    {
      "price": 1.22191,
      "volume": 503593446
    }
  ],
  "BIO": [
    {
      "price": 591,
      "volume": 1223497933
    },
    {
      "price": 591,
      "volume": 1223497933
    }
  ],
  "RSS3": [
    {
      "price": 99,
      "volume": 6498114
    },
    {
      "price": 99,
      "volume": 6498114
    }
  ],
  "CTSI": [
    {
      "price": 550,
      "volume": 59523450
    },
    {
      "price": 550,
      "volume": 59523450
    }
  ],
  "CKB": [
    {
      "price": 25,
      "volume": 15213568
    },
    {
      "price": 25,
      "volume": 15213568
    }
  ],
  "GRIFFAIN": [
    {
      "price": 352.165,
      "volume": 341282100
    },
    {
      "price": 352.165,
      "volume": 341282100
    }
  ],
  "MUBARAK": [
    {
      "price": 254.024,
      "volume": 57962471
    },
    {
      "price": 254.024,
      "volume": 57962471
    }
  ],
  "RDNT": [
    {
      "price": 33,
      "volume": 79369762
    },
    {
      "price": 33,
      "volume": 79369762
    }
  ],
  "SKYA": [
    {
      "price": 12,
      "volume": 37431811
    },
    {
      "price": 12,
      "volume": 37431811
    }
  ],
  "NFP": [
    {
      "price": 267,
      "volume": 17088152
    },
    {
      "price": 267,
      "volume": 17088152
    }
  ],
  "AIXBT": [
    {
      "price": 487,
      "volume": 21070757
    },
    {
      "price": 487,
      "volume": 21070757
    }
  ],
  "AEVO": [
    {
      "price": 450,
      "volume": 45047964
    },
    {
      "price": 450,
      "volume": 45047964
    }
  ],
  "TROLLSOL": [
    {
      "price": 305.05,
      "volume": 899326769
    },
    {
      "price": 305.05,
      "volume": 899326769
    }
  ],
  "DOGS": [
    {
      "price": 0.53,
      "volume": 8518876
    },
    {
      "price": 0.53,
      "volume": 8518876
    }
  ],
  "BMT": [
    {
      "price": 270,
      "volume": 326338
    },
    {
      "price": 270,
      "volume": 326338
    }
  ],
  "CGPT": [
    {
      "price": 467,
      "volume": 36215374
    },
    {
      "price": 467,
      "volume": 36215374
    }
  ],
  "STO": [
    {
      "price": 1564,
      "volume": 925933512
    },
    {
      "price": 1564,
      "volume": 925933512
    }
  ],
  "FUN": [
    {
      "price": 6.5,
      "volume": 260712037
    },
    {
      "price": 6.5,
      "volume": 260712037
    }
  ],
  "ATH": [
    {
      "price": 101,
      "volume": 4156401
    },
    {
      "price": 101,
      "volume": 4156401
    }
  ],
  "L3": [
    {
      "price": 232,
      "volume": 4443580508
    },
    {
      "price": 232,
      "volume": 4443580508
    }
  ],
  "SUNDOG": [
    {
      "price": 83,
      "volume": 15029966
    },
    {
      "price": 83,
      "volume": 15029966
    }
  ],
  "CELR": [
    {
      "price": 48,
      "volume": 654138
    },
    {
      "price": 48,
      "volume": 654138
    }
  ],
  "SPK": [
    {
      "price": 631,
      "volume": 145767942
    },
    {
      "price": 631,
      "volume": 145767942
    }
  ],
  "LRC": [
    {
      "price": 295,
      "volume": 10351920
    },
    {
      "price": 295,
      "volume": 10351920
    }
  ],
  "BLUR": [
    {
      "price": 476,
      "volume": 14268204
    },
    {
      "price": 476,
      "volume": 14268204
    }
  ],
  "CHILLGUY": [
    {
      "price": 198,
      "volume": 138335179
    },
    {
      "price": 198,
      "volume": 138335179
    }
  ],
  "CHR": [
    {
      "price": 372,
      "volume": 367334
    },
    {
      "price": 372,
      "volume": 367334
    }
  ],
  "ACH": [
    {
      "price": 121,
      "volume": 88208207
    },
    {
      "price": 121,
      "volume": 88208207
    }
  ],
  "NOM": [
    {
      "price": 51.824,
      "volume": 3219052845
    },
    {
      "price": 51.824,
      "volume": 3219052845
    }
  ],
  "RSR": [
    {
      "price": 30,
      "volume": 13384922
    },
    {
      "price": 30,
      "volume": 13384922
    }
  ],
  "HUMA": [
    {
      "price": 383.771,
      "volume": 2097702
    },
    {
      "price": 383.771,
      "volume": 2097702
    }
  ],
  "HFT": [
    {
      "price": 251,
      "volume": 9318368
    },
    {
      "price": 251,
      "volume": 9318368
    }
  ],
  "MOG": [
    {
      "price": 0.002594,
      "volume": 228400303
    },
    {
      "price": 0.002594,
      "volume": 228400303
    }
  ],
  "PRCL": [
    {
      "price": 235,
      "volume": 319530
    },
    {
      "price": 235,
      "volume": 319530
    }
  ],
  "BANANA": [
    {
      "price": 65635,
      "volume": 548428
    },
    {
      "price": 65635,
      "volume": 548428
    }
  ],
  "PEOPLE": [
    {
      "price": 127,
      "volume": 9851964
    },
    {
      "price": 127,
      "volume": 9851964
    }
  ],
  "MEW": [
    {
      "price": 10.48,
      "volume": 57966603
    },
    {
      "price": 10.48,
      "volume": 57966603
    }
  ],
  "STIK": [
    {
      "price": 4327,
      "volume": 5574581
    },
    {
      "price": 4327,
      "volume": 5574581
    }
  ],
  "BOME": [
    {
      "price": 8,
      "volume": 156980060
    },
    {
      "price": 8,
      "volume": 156980060
    }
  ],
  "KOMA": [
    {
      "price": 120.002,
      "volume": 15950047
    },
    {
      "price": 120.002,
      "volume": 15950047
    }
  ],
  "VINE": [
    {
      "price": 258,
      "volume": 5098853
    },
    {
      "price": 258,
      "volume": 5098853
    }
  ],
  "PIXEL": [
    {
      "price": 139,
      "volume": 21829929
    },
    {
      "price": 139,
      "volume": 21829929
    }
  ],
  "IOTX": [
    {
      "price": 79,
      "volume": 103936112
    },
    {
      "price": 79,
      "volume": 103936112
    }
  ],
  "KMNO": [
    {
      "price": 356,
      "volume": 3824765
    },
    {
      "price": 356,
      "volume": 3824765
    }
  ],
  "PONKE": [
    {
      "price": 468,
      "volume": 1322980
    },
    {
      "price": 468,
      "volume": 1322980
    }
  ],
  "HAEDAL": [
    {
      "price": 541,
      "volume": 1637397
    },
    {
      "price": 541,
      "volume": 1637397
    }
  ],
  "SHELL": [
    {
      "price": 592,
      "volume": 26970976
    },
    {
      "price": 592,
      "volume": 26970976
    }
  ],
  "GIGA": [
    {
      "price": 28,
      "volume": 20474865
    },
    {
      "price": 28,
      "volume": 20474865
    }
  ],
  "BRETT": [
    {
      "price": 125,
      "volume": 63035267
    },
    {
      "price": 125,
      "volume": 63035267
    }
  ],
  "GOAT": [
    {
      "price": 296,
      "volume": 201574558
    },
    {
      "price": 296,
      "volume": 201574558
    }
  ],
  "TURBO": [
    {
      "price": 19.99,
      "volume": 20083507
    },
    {
      "price": 19.99,
      "volume": 20083507
    }
  ],
  "BICO": [
    {
      "price": 429,
      "volume": 1681101
    },
    {
      "price": 429,
      "volume": 1681101
    }
  ],
  "PUMP": [
    {
      "price": 32.295,
      "volume": 429704831
    },
    {
      "price": 32.295,
      "volume": 429704831
    }
  ],
  "CHEEMS": [
    {
      "price": 0.010495,
      "volume": 6212198
    },
    {
      "price": 0.010495,
      "volume": 6212198
    }
  ],
  "RFC": [
    {
      "price": 11.024,
      "volume": 724533732
    },
    {
      "price": 11.024,
      "volume": 724533732
    }
  ],
  "FLOKI": [
    {
      "price": 0.557853,
      "volume": 52529043
    },
    {
      "price": 0.557853,
      "volume": 52529043
    }
  ],
  "SOLV": [
    {
      "price": 87,
      "volume": 758910825
    },
    {
      "price": 87,
      "volume": 758910825
    }
  ],
  "HOT": [
    {
      "price": 8,
      "volume": 361924
    },
    {
      "price": 8,
      "volume": 361924
    }
  ],
  "SKL": [
    {
      "price": 117,
      "volume": 428903
    },
    {
      "price": 117,
      "volume": 428903
    }
  ],
  "AMP": [
    {
      "price": 15,
      "volume": 4741592
    },
    {
      "price": 15,
      "volume": 4741592
    }
  ],
  "SAHARA": [
    {
      "price": 383,
      "volume": 17385132
    },
    {
      "price": 383,
      "volume": 17385132
    }
  ],
  "NPC": [
    {
      "price": 133,
      "volume": 708191
    },
    {
      "price": 133,
      "volume": 708191
    }
  ],
  "DGB": [
    {
      "price": 66,
      "volume": 79591606
    },
    {
      "price": 66,
      "volume": 79591606
    }
  ],
  "XEM": [
    {
      "price": 14,
      "volume": 276245438
    },
    {
      "price": 14,
      "volume": 276245438
    }
  ],
  "DEGEN": [
    {
      "price": 12,
      "volume": 43689833
    },
    {
      "price": 12,
      "volume": 43689833
    }
  ],
  "MOCA": [
    {
      "price": 249,
      "volume": 0
    },
    {
      "price": 249,
      "volume": 0
    }
  ],
  "SLP": [
    {
      "price": 12,
      "volume": 40105806
    },
    {
      "price": 12,
      "volume": 40105806
    }
  ],
  "MEME": [
    {
      "price": 9,
      "volume": 28173096
    },
    {
      "price": 9,
      "volume": 28173096
    }
  ],
  "ALT": [
    {
      "price": 7,
      "volume": 35856719
    },
    {
      "price": 7,
      "volume": 35856719
    }
  ],
  "TLM": [
    {
      "price": 32,
      "volume": 3894137
    },
    {
      "price": 32,
      "volume": 3894137
    }
  ],
  "SENT": [
    {
      "price": 294.004,
      "volume": 1767245
    },
    {
      "price": 294.004,
      "volume": 1767245
    }
  ],
  "AZTEC": [
    {
      "price": 335.938,
      "volume": 5262682
    },
    {
      "price": 335.938,
      "volume": 5262682
    }
  ],
  "PLUME": [
    {
      "price": 206,
      "volume": 3562096
    },
    {
      "price": 206,
      "volume": 3562096
    }
  ],
  "WOO": [
    {
      "price": 330,
      "volume": 3239967
    },
    {
      "price": 330,
      "volume": 3239967
    }
  ],
  "RARE": [
    {
      "price": 308,
      "volume": 14756280
    },
    {
      "price": 308,
      "volume": 14756280
    }
  ],
  "LOOKS": [
    {
      "price": 6,
      "volume": 5734332
    },
    {
      "price": 6,
      "volume": 5734332
    }
  ],
  "LINEA": [
    {
      "price": 60,
      "volume": 33577497
    },
    {
      "price": 60,
      "volume": 33577497
    }
  ],
  "GRT": [
    {
      "price": 418,
      "volume": 11521391
    },
    {
      "price": 418,
      "volume": 11521391
    }
  ],
  "REZ": [
    {
      "price": 75,
      "volume": 2635085
    },
    {
      "price": 75,
      "volume": 2635085
    }
  ],
  "ANIME": [
    {
      "price": 85.996,
      "volume": 3574928
    },
    {
      "price": 85.996,
      "volume": 3574928
    }
  ],
  "POND": [
    {
      "price": 41.006,
      "volume": 1766149
    },
    {
      "price": 41.006,
      "volume": 1766149
    }
  ],
  "SQD": [
    {
      "price": 529,
      "volume": 32665263
    },
    {
      "price": 529,
      "volume": 32665263
    }
  ],
  "MOVE": [
    {
      "price": 300,
      "volume": 4439518
    },
    {
      "price": 300,
      "volume": 4439518
    }
  ],
  "HMSTR": [
    {
      "price": 2.724,
      "volume": 1792762
    },
    {
      "price": 2.724,
      "volume": 1792762
    }
  ],
  "EDEN": [
    {
      "price": 583,
      "volume": 3934938
    },
    {
      "price": 583,
      "volume": 3934938
    }
  ],
  "OGN": [
    {
      "price": 388,
      "volume": 169937
    },
    {
      "price": 388,
      "volume": 169937
    }
  ],
  "VANRY": [
    {
      "price": 92,
      "volume": 10384184
    },
    {
      "price": 92,
      "volume": 10384184
    }
  ]
}